{
    "id": "crono_embalar_maquina_grande_manga_caixa_4kg_com_papel_09",
    "origem_registro": "cronoanalise",
    "tipo_atividade": "operacao",
    "atividade": "Embalar",
    "descricao": "Embalar",
    "observacao": "Inserção automática Máquina Grande",
    "grupo_embalagem": "Manga - caixa 4Kg - Com Papel",
    "variacao": "",
    "calibre": "09",
    "chave_tecnica": "manga_caixa_4kg_com_papel_09",
    "setor": "Máquina Grande",
    "setor_id": "",
    "linha": "",
    "linha_id": "",
    "linha_ref_id": "",
    "posto": "",
    "posto_id": "",
    "post_index": 0,
    "tipo_calculo": "ESTATICA",
    "tipo_operacao": "ESTATICA",
    "unidade_base": "Caixa",
    "unidade_carga": "Caixa",
    "qtd_base": 9,
    "qtd_ref": 1,
    "numero_frutos": 1,
    "num_frutos": 1,
    "tempo_s": 24.57,
    "tempo_cx_s": 24.57,
    "tempo_caixa_s": 24.57,
    "tempo_total_s": 24.57,
    "tempo_deslocamento_s": 0,
    "tempo_operacao_s": 24.57,
    "tempo_unitario": 24.57,
    "prod_h": 146.5201465201465,
    "distancia_m": 0,
    "velocidade_m_min": 0,
    "tipo_transporte": "",
    "fluxo_bpm_id": "",
    "codigo_arvore_estrutura": "",
    "origem": "",
    "destino": "",
    "meio_transporte": "",
    "operadores": 0,
    "TR": 24.57,
    "TN": 24.57,
    "TP": 24.57,
    "tolerancias": [],
    "fator_ritmo": 1,
    "fator_tolerancia": 1,
    "criado_em": "2026-05-18 01:03:41",
    "atualizado_em": "2026-05-18 17:49:02",
    "quantidade_ref": 1,
    "peso_fruto_g": 0,
    "tr": 24.57,
    "tn": 24.57,
    "tp": 24.57,
    "tempo_unitario_utilizado": 24.57,
    "schema_version": 1
}
