{
    "id": "transp_20260518132221_9887",
    "origem_registro": "cronoanalise",
    "tipo_atividade": "transporte",
    "atividade": "Puxar pallet fruta in natura -  >",
    "descricao": "Puxar pallet fruta in natura -  >",
    "observacao": "",
    "grupo_embalagem": "Componente",
    "variacao": "",
    "calibre": "",
    "chave_tecnica": "Componente",
    "setor": "Máquina Grande",
    "setor_id": "cod_12_05_setor_1",
    "linha": "Alimentação",
    "linha_id": "cod_12_05_linha_20260515021527_6300",
    "linha_ref_id": "cod_12_05_linha_20260515021527_6300",
    "posto": "Posto 0",
    "posto_id": "",
    "post_index": 0,
    "produto_id": "item_20260513173443_6953",
    "item": "",
    "item_carga": "",
    "tipo_calculo": "TRANSPORTE",
    "tipo_operacao": "TRANSPORTE",
    "unidade_base": "un",
    "unidade_carga": "un",
    "qtd_base": 1,
    "qtd_ref": 1,
    "numero_frutos": 1,
    "num_frutos": 1,
    "peso_fruto_g": 0,
    "er": 0,
    "tempo_s": 180,
    "tempo_cx_s": 180,
    "tempo_caixa_s": 180,
    "tempo_fruto_s": 180,
    "tempo_total_s": 180,
    "tempo_deslocamento_s": 0,
    "tempo_operacao_s": 180,
    "tempo_unitario": 180,
    "prod_h": 20,
    "distancia_m": 0,
    "velocidade_m_s": 0,
    "velocidade_m_min": 0,
    "tipo_transporte": "",
    "fluxo_bpm_id": "",
    "codigo_arvore_estrutura": "",
    "origem": "",
    "destino": "",
    "meio_transporte": "",
    "operadores": 0,
    "TR": 180,
    "TN": 180,
    "TP": 180,
    "tolerancias": [
        {
            "categoria": "Pessoal",
            "descricao": "Necessidades pessoais",
            "percentual": 0,
            "ativo": true
        },
        {
            "categoria": "Fadiga",
            "descricao": "Esforco, postura, repetitividade",
            "percentual": 0,
            "ativo": true
        },
        {
            "categoria": "Ambiente",
            "descricao": "Calor, ruido, umidade, iluminacao",
            "percentual": 0,
            "ativo": true
        },
        {
            "categoria": "Espera inevitavel",
            "descricao": "Pequenas paradas inevitaveis",
            "percentual": 0,
            "ativo": true
        },
        {
            "categoria": "Operacional especifica",
            "descricao": "Condicao especial da atividade",
            "percentual": 0,
            "ativo": true
        }
    ],
    "fator_ritmo": 1,
    "fator_tolerancia": 1,
    "criado_em": "2026-05-18 13:22:21",
    "atualizado_em": "2026-05-20 12:16:35",
    "schema_version": 1
}
